buildspan/__init__.py
buildspan/gitci.py
buildpan-0.0.22.dist-info/LICENCE
buildpan-0.0.22.dist-info/METADATA
buildpan-0.0.22.dist-info/WHEEL
buildpan-0.0.22.dist-info/entry_points.txt
buildpan-0.0.22.dist-info/top_level.txt
buildpan-0.0.22.dist-info/RECORD
